pysolcast/__init__.py
pysolcast/base.py
pysolcast/exceptions.py
pysolcast/rooftop.py
pysolcast/utility.py
pysolcast/weather.py
pysolcast/world.py
pysolcast-2.0.7.dist-info/AUTHORS.rst
pysolcast-2.0.7.dist-info/LICENSE
pysolcast-2.0.7.dist-info/METADATA
pysolcast-2.0.7.dist-info/WHEEL
pysolcast-2.0.7.dist-info/RECORD
