Metadata-Version: 2.3
Name: pysolcast
Version: 2.0.7
Summary: 
Author: Nathaniel McAuliffe
Author-email: nathanielmcauliffe@hotmail.com
Requires-Python: >=3.9
Classifier: Programming Language :: Python :: 3
Classifier: Programming Language :: Python :: 3.9
Classifier: Programming Language :: Python :: 3.10
Classifier: Programming Language :: Python :: 3.11
Classifier: Programming Language :: Python :: 3.12
Classifier: Programming Language :: Python :: 3.13
Requires-Dist: anyconfig (==0.14.0)
Requires-Dist: isodate (==0.7.2)
Requires-Dist: requests (>=2.31.0,<3.0.0)
